inspect4j/__init__.py
inspect4j/java_inspector.py
inspect4j/java_utils.py
inspect4j/main.py
inspect4j/structure_tree.py
inspect4j/licenses/apache-2.0.txt
inspect4j/licenses/bsd-3-clause.txt
inspect4j/licenses/gpl-3.0.txt
inspect4j/licenses/lgpl-3.0.txt
inspect4j/licenses/mit.txt
inspect4j-1.0.0.dist-info/LICENSE
inspect4j-1.0.0.dist-info/METADATA
inspect4j-1.0.0.dist-info/WHEEL
inspect4j-1.0.0.dist-info/entry_points.txt
inspect4j-1.0.0.dist-info/top_level.txt
inspect4j-1.0.0.dist-info/RECORD
