Metadata-Version: 2.1
Name: inspect4j
Version: 1.0.0
Summary: Static code analysis tool for Java repositories
Home-page: https://git.ecdf.ed.ac.uk/msc-24-25/inspect4j.git
Author: Liru Qu
License: MIT
Platform: UNKNOWN
Classifier: Development Status :: 4 - Beta
Classifier: Intended Audience :: Developers
Classifier: License :: OSI Approved :: MIT License
Classifier: Programming Language :: Python :: 3
Classifier: Programming Language :: Python :: 3.7
Classifier: Programming Language :: Python :: 3.8
Classifier: Programming Language :: Python :: 3.9
Classifier: Programming Language :: Python :: 3.10
Classifier: Programming Language :: Python :: 3.11
Classifier: Topic :: Software Development :: Libraries :: Python Modules
Classifier: Topic :: Software Development :: Quality Assurance
Classifier: Operating System :: OS Independent
Requires-Python: >=3.7
Requires-Dist: javalang
Requires-Dist: click
Requires-Dist: json2html
Requires-Dist: gitpython
Requires-Dist: requests
Requires-Dist: chardet
